setup.py
sanketh_date_formatter/sanketh_date_formatter.py
sanketh_date_formatter.egg-info/PKG-INFO
sanketh_date_formatter.egg-info/SOURCES.txt
sanketh_date_formatter.egg-info/dependency_links.txt
sanketh_date_formatter.egg-info/top_level.txt